signxml/__init__.py
signxml/exceptions.py
signxml/schemas/xmldsig-core-schema.xsd
signxml/schemas/xmldsig1-schema.xsd
signxml/schemas/xmldsig11-schema.xsd
signxml/util/__init__.py
signxml_openadr-2.9.1.dist-info/LICENSE
signxml_openadr-2.9.1.dist-info/METADATA
signxml_openadr-2.9.1.dist-info/WHEEL
signxml_openadr-2.9.1.dist-info/top_level.txt
signxml_openadr-2.9.1.dist-info/RECORD
