Metadata-Version: 2.1
Name: signxml-openadr
Version: 2.9.1
Summary: Python XML Signature library
Home-page: https://github.com/kislyuk/signxml
Author: UNKNOWN
Author-email: UNKNOWN
License: Apache Software License
Platform: MacOS X
Platform: Posix
Classifier: Intended Audience :: Developers
Classifier: License :: OSI Approved :: Apache Software License
Classifier: Operating System :: MacOS :: MacOS X
Classifier: Operating System :: POSIX
Classifier: Programming Language :: Python
Classifier: Programming Language :: Python :: 2.7
Classifier: Programming Language :: Python :: 3.4
Classifier: Programming Language :: Python :: 3.5
Classifier: Programming Language :: Python :: 3.6
Classifier: Programming Language :: Python :: 3.7
Classifier: Topic :: Software Development :: Libraries :: Python Modules
Requires-Dist: lxml (<5,>=4.2.1)
Requires-Dist: eight (<2,>=0.4.2)
Requires-Dist: cryptography (<4,>=2.1.4)
Requires-Dist: pyOpenSSL (<20,>=17.5.0)
Requires-Dist: certifi (>=2018.1.18)
Requires-Dist: enum34 (<2,>=1.1.6) ; python_version == "2.7"
Requires-Dist: ipaddress (<2,>=1.0.17) ; python_version == "2.7"
